visidex/detection/__init__.py
visidex/detection/rekd.py
visidex/detection/singular_point.py
visidex/kornia_local_feature/__init__.py
visidex/kornia_local_feature/descriptor_mixins.py
visidex/kornia_local_feature/detector_mixins.py
visidex/kornia_local_feature/local_feature_custons.py
visidex/model/__init__.py
visidex/model/data_accessors.py
visidex/retrieval/__init__.py
visidex/utils/__init__.py
visidex/utils/config.py
visidex/utils/download.py
visidex/utils/evaluation.py
visidex/utils/kernels.py
visidex/utils/random_data.py
visidex-0.2.7.dist-info/METADATA
visidex-0.2.7.dist-info/WHEEL
visidex-0.2.7.dist-info/RECORD
